audit_log/__init__.py
audit_log/formatter.py
audit_log/logger.py
datapunt_audit_log-0.4.0.dist-info/LICENSE
datapunt_audit_log-0.4.0.dist-info/METADATA
datapunt_audit_log-0.4.0.dist-info/WHEEL
datapunt_audit_log-0.4.0.dist-info/top_level.txt
datapunt_audit_log-0.4.0.dist-info/RECORD
