Metadata-Version: 2.1
Name: datapunt-audit-log
Version: 0.4.0
Summary: A simple python package to enable uniform audit logging
Home-page: https://github.com/Amsterdam/auditlog
Author: Datapunt Amsterdam
Author-email: datapunt@amsterdam.nl
License: Mozilla Public License 2.0
Platform: UNKNOWN
Classifier: Environment :: Web Environment
Classifier: Framework :: Django
Classifier: Framework :: Django :: 2.2
Classifier: Intended Audience :: Developers
Classifier: License :: OSI Approved :: Mozilla Public License 2.0 (MPL 2.0)
Classifier: Operating System :: OS Independent
Classifier: Programming Language :: Python
Classifier: Programming Language :: Python :: 3.5
Classifier: Programming Language :: Python :: 3.6
Classifier: Topic :: Internet :: WWW/HTTP
Classifier: Topic :: Internet :: WWW/HTTP :: Dynamic Content
Classifier: Topic :: System :: Logging
Provides-Extra: dev
Requires-Dist: pytest ; extra == 'dev'
Requires-Dist: pytest-cov ; extra == 'dev'
Requires-Dist: twine ; extra == 'dev'
Requires-Dist: bump2version ; extra == 'dev'
